merge_sorted_files/__init__.py
merge_sorted_files/iterator.py
merge_sorted_files/main.py
merge_sorted_files/reader.py
merge_sorted_files-0.1.1.dist-info/entry_points.txt
merge_sorted_files-0.1.1.dist-info/LICENSE
merge_sorted_files-0.1.1.dist-info/WHEEL
merge_sorted_files-0.1.1.dist-info/METADATA
merge_sorted_files-0.1.1.dist-info/RECORD
