Metadata-Version: 2.1
Name: merge-sorted-files
Version: 0.1.1
Summary: Merge sorted files and write output to disk
License: MIT
Author: Ilia Krets
Author-email: mrchair2170@gmail.com
Requires-Python: >=3.9,<4.0
Classifier: License :: OSI Approved :: MIT License
Classifier: Programming Language :: Python :: 3
Classifier: Programming Language :: Python :: 3.10
Classifier: Programming Language :: Python :: 3.9
Requires-Dist: click (>=8.0.3,<9.0.0)
Requires-Dist: tqdm (>=4.62.3,<5.0.0)
